carbonsignal/__init__.py
carbonsignal/api/__init__.py
carbonsignal/api/authentication/__init__.py
carbonsignal/api/authentication/check_login_provider_v1_0_auth_login_provider_post.py
carbonsignal/api/authentication/get_invite_token_v1_0_auth_invites_token_id_get.py
carbonsignal/api/authentication/login_v1_0_auth_login_post.py
carbonsignal/api/authentication/logout_v1_0_auth_logout_post.py
carbonsignal/api/authentication/refresh_token_v1_0_auth_refresh_token_post.py
carbonsignal/api/authentication/register_v1_0_auth_register_post.py
carbonsignal/api/authentication/register_with_invite_token_v1_0_auth_register_invites_token_id_post.py
carbonsignal/api/authentication/request_password_token_v1_0_auth_reset_password_post.py
carbonsignal/api/authentication/reset_password_v1_0_auth_forgot_password_tokens_token_id_post.py
carbonsignal/api/authentication/sso_redirect_v1_0_auth_sso_provider_id_login_get.py
carbonsignal/api/authentication/update_password_v1_0_auth_passwords_post.py
carbonsignal/api/building_exports/__init__.py
carbonsignal/api/building_exports/get_building_export_v1_0_buildings_building_id_export_get.py
carbonsignal/api/building_results/__init__.py
carbonsignal/api/building_results/analyze_interventions_bulk_v1_0_buildings_bulk_intervention_analysis_post.py
carbonsignal/api/building_results/analyze_interventions_v1_0_buildings_building_id_intervention_analysis_post.py
carbonsignal/api/building_results/generate_baseline_v1_0_buildings_building_id_baseline_post.py
carbonsignal/api/building_results/get_building_result_v1_0_buildings_building_id_results_get.py
carbonsignal/api/building_results/put_intervention_cost_v1_0_buildings_building_id_intervention_costs_intervention_type_put.py
carbonsignal/api/building_results/trigger_baseline_bulk_v1_0_buildings_bulk_baseline_analysis_post.py
carbonsignal/api/building_roles/__init__.py
carbonsignal/api/building_roles/create_building_role_v1_0_buildings_building_id_roles_post.py
carbon_signal_app_client-3.2.0.dist-info/LICENSE
carbon_signal_app_client-3.2.0.dist-info/METADATA
carbon_signal_app_client-3.2.0.dist-info/WHEEL
carbon_signal_app_client-3.2.0.dist-info/RECORD
