Metadata-Version: 2.3
Name: carbon-signal-app-client
Version: 3.2.0
Summary: A client library for accessing Carbon Signal API
Author: Carbon Signal
Author-email: info@carbonsignal.com
Requires-Python: >=3.10,<4.0
Classifier: Programming Language :: Python :: 3
Classifier: Programming Language :: Python :: 3.10
Classifier: Programming Language :: Python :: 3.11
Classifier: Programming Language :: Python :: 3.12
Classifier: Programming Language :: Python :: 3.13
Requires-Dist: attrs (>=22.2.0)
Requires-Dist: httpx (>=0.20.0,<0.29.0)
Requires-Dist: python-dateutil (>=2.8.0)
Project-URL: Documentation, https://Carbon-Signal.github.io/carbon-signal-app-client/
Project-URL: Repository, https://github.com/Carbon-Signal/carbon-signal-app-client
